PDFReport/__init__.py
PDFReport/__main__.py
PDFReport/barcodeframe.py
PDFReport/border.py
PDFReport/boxframe.py
PDFReport/breakframe.py
PDFReport/containerframe.py
PDFReport/enums.py
PDFReport/globals.py
PDFReport/imageframe.py
PDFReport/lineframe.py
PDFReport/pageformat.py
PDFReport/pageframe.py
PDFReport/pen.py
PDFReport/positionframe.py
PDFReport/rect.py
PDFReport/renderer.py
PDFReport/report.py
PDFReport/reportdata.py
PDFReport/reportframe.py
PDFReport/serialframe.py
PDFReport/simpleframe.py
PDFReport/size.py
PDFReport/sizestate.py
PDFReport/tablecell.py
PDFReport/tablecolumn.py
PDFReport/tableframe.py
PDFReport/tablerow.py
PDFReport/textframe.py
PDFReport/textstyle.py
PDFReport/textstyles.py
PDFReport-1.0.1.dist-info/LICENSE
PDFReport-1.0.1.dist-info/METADATA
PDFReport-1.0.1.dist-info/WHEEL
PDFReport-1.0.1.dist-info/top_level.txt
PDFReport-1.0.1.dist-info/RECORD
