Metadata-Version: 2.1
Name: PDFReport
Version: 1.0.1
Summary: Create PDF reports
Author-email: Michael Hodel <info@adiuvaris.ch>
License: MIT License
Project-URL: Homepage, https://github.com/adiuvaris/PDFReport
Keywords: PDF,report,generator,library
Classifier: License :: OSI Approved :: MIT License
Classifier: Programming Language :: Python
Classifier: Programming Language :: Python :: 3
Requires-Python: >=3.11
License-File: LICENSE
Requires-Dist: fpdf2 >=2.7.6
Requires-Dist: Pillow >=10.1.0
Requires-Dist: qrcode >=7.4.2
Requires-Dist: python-barcode >=0.15.1
Provides-Extra: dev
Requires-Dist: black ; extra == 'dev'
Requires-Dist: bumpver ; extra == 'dev'
Requires-Dist: isort ; extra == 'dev'
Requires-Dist: pip-tools ; extra == 'dev'
Requires-Dist: pytest ; extra == 'dev'
Requires-Dist: build ; extra == 'dev'
Requires-Dist: twine ; extra == 'dev'
Requires-Dist: sphinx ; extra == 'dev'
Requires-Dist: furo ; extra == 'dev'
